odoo8_addon_medical_prescription-8.0.1.1.0.99.dev4-py2.7-nspkg.pth
odoo8_addon_medical_prescription-8.0.1.1.0.99.dev4.dist-info/DESCRIPTION.rst
odoo8_addon_medical_prescription-8.0.1.1.0.99.dev4.dist-info/METADATA
odoo8_addon_medical_prescription-8.0.1.1.0.99.dev4.dist-info/RECORD
odoo8_addon_medical_prescription-8.0.1.1.0.99.dev4.dist-info/WHEEL
odoo8_addon_medical_prescription-8.0.1.1.0.99.dev4.dist-info/metadata.json
odoo8_addon_medical_prescription-8.0.1.1.0.99.dev4.dist-info/namespace_packages.txt
odoo8_addon_medical_prescription-8.0.1.1.0.99.dev4.dist-info/top_level.txt
odoo_addons/medical_prescription/README.rst
odoo_addons/medical_prescription/__init__.py
odoo_addons/medical_prescription/__openerp__.py
odoo_addons/medical_prescription/data/ir_sequence.xml
odoo_addons/medical_prescription/i18n/pt_BR.po
odoo_addons/medical_prescription/i18n/sl.po
odoo_addons/medical_prescription/models/__init__.py
odoo_addons/medical_prescription/models/medical_prescription_order.py
odoo_addons/medical_prescription/models/medical_prescription_order_line.py
odoo_addons/medical_prescription/security/ir.model.access.csv
odoo_addons/medical_prescription/views/medical_prescription_order_line_view.xml
odoo_addons/medical_prescription/views/medical_prescription_order_view.xml
