Metadata-Version: 2.0
Name: odoo8-addon-medical-prescription
Version: 8.0.1.1.0.99.dev4
Summary: This module introduce the prescription/prescription line into the medical addons.
Home-page: http://www.acsone.eu
Author: ACSONE SA/NV, Odoo Community Association (OCA)
Author-email: support@odoo-community.org
License: AGPL-3
Platform: UNKNOWN
Classifier: Programming Language :: Python :: 2.7
Classifier: Framework :: Odoo
Classifier: License :: OSI Approved :: GNU Affero General Public License v3
Requires-Dist: odoo (<9.0a,>=8.0a)
Requires-Dist: odoo8-addon-medical
Requires-Dist: odoo8-addon-medical-medicament
Requires-Dist: odoo8-addon-medical-medication
